MANIFEST.in
README.rst
setup.py
src/digimat/__init__.py
src/digimat.espa.egg-info/PKG-INFO
src/digimat.espa.egg-info/SOURCES.txt
src/digimat.espa.egg-info/dependency_links.txt
src/digimat.espa.egg-info/namespace_packages.txt
src/digimat.espa.egg-info/not-zip-safe
src/digimat.espa.egg-info/requires.txt
src/digimat.espa.egg-info/top_level.txt
src/digimat/espa/__init__.py
src/digimat/espa/espa.py
src/digimat/espa/link.py
src/digimat/espa/notification.py