Metadata-Version: 1.0
Name: digimat.espa
Version: 0.1.9
Summary: Digimat ESPA 4.4.4
Home-page: https://github.com/digimat/digimat-espa
Author: Frederic Hess
Author-email: fhess@st-sa.ch
License: PSF
Platform: UNKNOWN
